dima_test_sdk/__init__.py
dima_test_sdk/api_client.py
dima_test_sdk/api_response.py
dima_test_sdk/configuration.py
dima_test_sdk/exceptions.py
dima_test_sdk/py.typed
dima_test_sdk/rest.py
dima_test_sdk/api/__init__.py
dima_test_sdk/api/accounting_api.py
dima_test_sdk/api/adjustments_api.py
dima_test_sdk/api/background_checks_api.py
dima_test_sdk/api/candidates_api.py
dima_test_sdk/api/carta_api.py
dima_test_sdk/api/consent_api.py
dima_test_sdk/api/contractors_api.py
dima_test_sdk/api/contracts_api.py
dima_test_sdk/api/custom_fields_api.py
dima_test_sdk/api/deel_as_a_service_api.py
dima_test_sdk/api/default_api.py
dima_test_sdk/api/employees_api.py
dima_test_sdk/api/enrollments_api.py
dima_test_sdk/api/eor_api.py
dima_test_sdk/api/equity_api.py
dima_test_sdk/api/global_payroll_api.py
dima_test_sdk/api/groups_api.py
dima_test_sdk/api/immigration_api.py
dima_test_sdk/api/integrations_api.py
dima_test_sdk/api/invoices_api.py
dima_test_sdk/api/legal_entities_api.py
dima_test_sdk/api/loans_api.py
dima_test_sdk/api/lookups_api.py
dima_test_sdk/api/managers_api.py
dima_test_sdk/api/milestones_api.py
dima_test_sdk/api/off_cycle_payments_api.py
dima_test_sdk/api/offboarding_api.py
dima_test_sdk/api/onboarding_api.py
dima_test_sdk/api/organization_structure_api.py
dima_test_sdk/api/organizations_api.py
dima_test_sdk/api/partner_managed_api.py
dima_test_sdk/api/payouts_api.py
dima_test_sdk/api/payroll_api.py
dima_test_sdk/api/paystubs_api.py
dima_test_sdk/api/people_api.py
dima_test_sdk/api/plans401_k_api.py
dima_test_sdk/api/positions_api.py
dima_test_sdk/api/reports_api.py
dima_test_sdk/api/screenings_api.py
dima_test_sdk/api/tasks_api.py
dima_test_sdk/api/time_off_api.py
dima_test_sdk/api/time_tracking_rates_api.py
dima_test_sdk/api/time_tracking_shifts_api.py
dima_test_sdk/api/timesheets_api.py
dima_test_sdk/api/token_api.py
dima_test_sdk/api/webhooks_api.py
dima_test_sdk/api/worker_relations_api.py
dima_test_sdk/api/workers_api.py
dima_test_sdk/models/__init__.py
dima_test_sdk-1.0.1.dist-info/METADATA
dima_test_sdk-1.0.1.dist-info/WHEEL
dima_test_sdk-1.0.1.dist-info/top_level.txt
dima_test_sdk-1.0.1.dist-info/RECORD
