Metadata-Version: 2.2
Name: dima-test-sdk
Version: 1.0.1
Summary: Dima REST API
Home-page: 
Author: Dima API Team
Author-email: dima@example.com
Keywords: OpenAPI,OpenAPI-Generator,Dima REST API
Requires-Dist: urllib3<3.0.0,>=1.25.3
Requires-Dist: python-dateutil>=2.8.2
Requires-Dist: pydantic>=2
Requires-Dist: typing-extensions>=4.7.1
Dynamic: author
Dynamic: author-email
Dynamic: description
Dynamic: description-content-type
Dynamic: keywords
Dynamic: requires-dist
Dynamic: summary
